yahoo_finance_pandas/__init__.py
yahoo_finance_pandas/dividends.py
yahoo_finance_pandas/options.py
yahoo_finance_pandas/stocks.py
yahoo_finance_pandas-1.0.3.dist-info/METADATA
yahoo_finance_pandas-1.0.3.dist-info/RECORD
yahoo_finance_pandas-1.0.3.dist-info/WHEEL
yahoo_finance_pandas-1.0.3.dist-info/top_level.txt
